{
    "LAYERSOURCE": {
        "LAYERSOURCE":"Layers Source",       
        "ADD": "Add Layer Source",
        "EDIT": "Edit Layer Source",  
        "VIEW":"View Layer Source",
        "NAME":"Name",
        "TYPE": "Type",
        "INTERNAL_LINK": "Internal Link",
        "EXTERNAL_LINK": "External Link",
        "USER": "User",
        "PASSWORD": "Password",
        "SELECT":"Select LayerSource",
        "TITLE_CONFIRM_DELETE":"LayerSource Delete",
        "CONFIRM_DELETE":"Do you really want to delete LayerSource??"
    }
}
